README.md
setup.py
topsis_101803545/Topsis.py
topsis_101803545.egg-info/PKG-INFO
topsis_101803545.egg-info/SOURCES.txt
topsis_101803545.egg-info/dependency_links.txt
topsis_101803545.egg-info/entry_points.txt
topsis_101803545.egg-info/top_level.txt