Metadata-Version: 2.1
Name: topsis-101803545
Version: 4.1.0
Summary: Python package to implement TOPSIS
Home-page: UNKNOWN
Author: Paramjot Singh
Author-email: paramjots78662@gmail.com
License: MIT
Platform: UNKNOWN
Classifier: License :: OSI Approved :: MIT License
Classifier: Programming Language :: Python :: 3
Classifier: Programming Language :: Python :: 3.7
